bn2vec/__init__.py
bn2vec/bn2vec_exceptions.py
bn2vec/feature_engineering/__init__.py
bn2vec/feature_engineering/bn2vec.py
bn2vec/feature_engineering/dnf2vec.py
bn2vec/feature_engineering/ens2mat.py
bn2vec/feature_engineering/obj2vec.py
bn2vec/feature_selection/__init__.py
bn2vec/feature_selection/bn_features_selector.py
bn2vec/rules_extraction/__init__.py
bn2vec/rules_extraction/decision_tree_classifier.py
bn2vec/rules_extraction/model_evaluation.py
bn2vec/rules_extraction/rules_extractor.py
bn2vec/utils/__init__.py
bn2vec/utils/bn_dataset.py
bn2vec/utils/configparser.py
bn2vec/utils/logger.py
bn2vec/utils/mathlib.py
bn2vec-1.0.0.dist-info/LICENSE
bn2vec-1.0.0.dist-info/METADATA
bn2vec-1.0.0.dist-info/WHEEL
bn2vec-1.0.0.dist-info/top_level.txt
bn2vec-1.0.0.dist-info/RECORD
