Metadata-Version: 2.1
Name: bn2vec
Version: 1.0.0
Summary: Boolean Network To Vector
Home-page: UNKNOWN
Author: Mohamed Hmini
Author-email: mo@mhmini.com
License: UNKNOWN
Platform: UNKNOWN
License-File: LICENSE
Requires-Dist: colomoto-jupyter (==0.8.2)
Requires-Dist: igraph (==0.9.9)
Requires-Dist: matplotlib (==3.5.1)
Requires-Dist: numpy (==1.22.2)
Requires-Dist: pandas (==1.4.1)
Requires-Dist: scikit-learn (==1.0.2)
Requires-Dist: tqdm (==4.63.0)
Requires-Dist: PyYAML
